pysnooapi/__init__.py
pysnooapi/__version__.py
pysnooapi/api.py
pysnooapi/const.py
pysnooapi/device.py
pysnooapi/errors.py
pysnooapi/request.py
pysnooapi/utils.py
pysnooapi-0.0.3.dist-info/LICENSE
pysnooapi-0.0.3.dist-info/METADATA
pysnooapi-0.0.3.dist-info/WHEEL
pysnooapi-0.0.3.dist-info/top_level.txt
pysnooapi-0.0.3.dist-info/RECORD
