Metadata-Version: 2.1
Name: pysnooapi
Version: 0.0.3
Summary: Python package for controlling Snoo Smart Sleepers from happiestbaby.com
Home-page: https://github.com/sanghviharshit/pysnoo
Author: Harshit Sanghvi
License: MIT
Classifier: License :: OSI Approved :: MIT License
Classifier: Programming Language :: Python
Classifier: Programming Language :: Python :: 3
Classifier: Programming Language :: Python :: 3.8
Classifier: Programming Language :: Python :: 3.9
Classifier: Programming Language :: Python :: Implementation :: CPython
Classifier: Programming Language :: Python :: Implementation :: PyPy
Requires-Python: >=3.8
License-File: LICENSE
Requires-Dist: aiohttp
Requires-Dist: pytz
